pyinstantmeshes/__init__.py
pyinstantmeshes/_pyinstantmeshes.cp314t-win32.pyd
pyinstantmeshes-1.0.0.dist-info/METADATA
pyinstantmeshes-1.0.0.dist-info/WHEEL
pyinstantmeshes-1.0.0.dist-info/licenses/LICENSE
pyinstantmeshes-1.0.0.dist-info/RECORD
