Metadata-Version: 2.2
Name: pyinstantmeshes
Version: 1.0.0
Summary: Python bindings for Instant Meshes - fast automatic retopology
Keywords: mesh,simplification,optimization,remeshing
Author-Email: Brett-Michael Green <brett@bmgvisualtech.com>
License: BSD-3-Clause
Classifier: Development Status :: 3 - Alpha
Classifier: Intended Audience :: Developers
Classifier: Natural Language :: English
Classifier: Programming Language :: Python :: 3
Classifier: Programming Language :: Python :: 3 :: Only
Classifier: Programming Language :: Python :: 3.11
Classifier: Programming Language :: Python :: 3.12
Classifier: Programming Language :: Python :: 3.13
Classifier: Programming Language :: Python :: 3.14
Classifier: Topic :: Multimedia :: Graphics :: 3D Modeling
Classifier: Topic :: Multimedia :: Graphics :: Graphics Conversion
Project-URL: Homepage, https://github.com/greenbrettmichael/pyinstantmeshes
Project-URL: Repository, https://github.com/greenbrettmichael/pyinstantmeshes
Requires-Python: >=3.11
Requires-Dist: numpy>=1.19.0
Provides-Extra: test
Requires-Dist: pytest>=7.0.0; extra == "test"
Requires-Dist: pytest-cov>=4.0.0; extra == "test"
